jetdb/__init__.py
jetdb-0.3.2.dist-info/WHEEL
jetdb-0.3.2.dist-info/METADATA
jetdb-0.3.2.dist-info/RECORD
