Metadata-Version: 2.1
Name: jetdb
Version: 0.3.2
Summary: This module is designed for everyone to easily handle txt files. JSON file handling will be added soon.
Author: Srijeet Aditya
Author-email: adityasrijeet12355@egmail.com
Requires-Python: >=3.8,<4.0
Classifier: Programming Language :: Python :: 3
Classifier: Programming Language :: Python :: 3.10
Classifier: Programming Language :: Python :: 3.8
Classifier: Programming Language :: Python :: 3.9
